Workbook
Name Slicer_Category: #N/A
Name Slicer_Country: #N/A
Name Slicer_Month: #N/A
Name Slicer_Product_Name: #N/A

Sheet Dashboard
B1: Q1 2024 PERFORMANCE DASHBOARD
B4: =Sheet3!F4 -> Total Revenue | H4: =Sheet3!F5 -> Total Profit | O4: =Sheet3!F6 -> Average Order Value | U4: =Sheet3!F7 -> Total Orders
B5: =Sheet3!I4 -> 2598.945 | H5: =Sheet3!I5 -> 934.395 | O5: =Sheet3!I6 -> 64.973625 | U5: =Sheet3!I7 -> 40

Sheet Data
A1: Order id | B1: Month | C1: Customer Name | D1: Product Name | E1: Category | F1: Quantity | G1: Unit Price | H1: Discount | I1: Shipping Cost | J1: Country | K1: Cogs Percentage | L1: Marketing Cost Per Unit | M1: Warehouse Cost Per Unit | N1: Revenue | O1: COGS | P1: Marketing Cost | Q1: Warehouse Cost | R1: Total Cost | S1: Profit | T1: Margin%
A2: 1001 | B2: Ene | C2: Maria Gonzalez | D2: Camiseta Básica Blanca | E2: Tops | F2: 2 | G2: 25 | H2: 0 | I2: 5.5 | J2: Costa Rica | K2: 0.35 | L2: 3 | M2: 1.5 | N2: =(Data[[#This Row],[Unit Price]]*Data[[#This Row],[Quantity]])-Data[[#This Row],[Discount]] -> 50 | O2: =Data[[#This Row],[Unit Price]]*Data[[#This Row],[Quantity]]*Data[[#This Row],[Cogs Percentage]] -> 17.5 | P2: =Data[[#This Row],[Marketing Cost Per Unit]]*Data[[#This Row],[Quantity]] -> 6 | Q2: =Data[[#This Row],[Warehouse Cost Per Unit]]*Data[[#This Row],[Quantity]] -> 3 | R2: =Data[[#This Row],[COGS]]+Data[[#This Row],[Marketing Cost]]+Data[[#This Row],[Warehouse Cost]]+Data[[#This Row],[Shipping Cost]] -> 32 | S2: =Data[[#This Row],[Revenue]]-Data[[#This Row],[Total Cost]] -> 18 | T2: =(Data[[#This Row],[Profit]]/Data[[#This Row],[Revenue]]) -> 0.36
A3: 1002 | B3: Ene | C3: Juan Perez | D3: Camiseta Básica Blanca | E3: Tops | F3: 1 | G3: 25 | H3: 0.025 | I3: 5.5 | J3: Mexico | K3: 0.35 | L3: 3 | M3: 1.5 | N3: =(Data[[#This Row],[Unit Price]]*Data[[#This Row],[Quantity]])-Data[[#This Row],[Discount]] -> 24.975 | O3: =Data[[#This Row],[Unit Price]]*Data[[#This Row],[Quantity]]*Data[[#This Row],[Cogs Percentage]] -> 8.75 | P3: =Data[[#This Row],[Marketing Cost Per Unit]]*Data[[#This Row],[Quantity]] -> 3 | Q3: =Data[[#This Row],[Warehouse Cost Per Unit]]*Data[[#This Row],[Quantity]] -> 1.5 | R3: =Data[[#This Row],[COGS]]+Data[[#This Row],[Marketing Cost]]+Data[[#This Row],[Warehouse Cost]]+Data[[#This Row],[Shipping Cost]] -> 18.75 | S3: =Data[[#This Row],[Revenue]]-Data[[#This Row],[Total Cost]] -> 6.225 | T3: =(Data[[#This Row],[Profit]]/Data[[#This Row],[Revenue]]) -> 0.24924925
A4: 1006 | B4: Ene | C4: Sofia Rodriguez | D4: Camiseta Básica Blanca | E4: Tops | F4: 3 | G4: 25 | H4: 0.0375 | I4: 5.5 | J4: Panama | K4: 0.35 | L4: 3 | M4: 1.5 | N4: =(Data[[#This Row],[Unit Price]]*Data[[#This Row],[Quantity]])-Data[[#This Row],[Discount]] -> 74.9625 | O4: =Data[[#This Row],[Unit Price]]*Data[[#This Row],[Quantity]]*Data[[#This Row],[Cogs Percentage]] -> 26.25 | P4: =Data[[#This Row],[Marketing Cost Per Unit]]*Data[[#This Row],[Quantity]] -> 9 | Q4: =Data[[#This Row],[Warehouse Cost Per Unit]]*Data[[#This Row],[Quantity]] -> 4.5 | R4: =Data[[#This Row],[COGS]]+Data[[#This Row],[Marketing Cost]]+Data[[#This Row],[Warehouse Cost]]+Data[[#This Row],[Shipping Cost]] -> 45.25 | S4: =Data[[#This Row],[Revenue]]-Data[[#This Row],[Total Cost]] -> 29.7125 | T4: =(Data[[#This Row],[Profit]]/Data[[#This Row],[Revenue]]) -> 0.39636485
A5: 1013 | B5: Ene | C5: Diego Morales | D5: Camiseta Básica Negra | E5: Tops | F5: 4 | G5: 25 | H5: 0.05 | I5: 5.5 | J5: Costa Rica | K5: 0.35 | L5: 3 | M5: 1.5 | N5: =(Data[[#This Row],[Unit Price]]*Data[[#This Row],[Quantity]])-Data[[#This Row],[Discount]] -> 99.95 | O5: =Data[[#This Row],[Unit Price]]*Data[[#This Row],[Quantity]]*Data[[#This Row],[Cogs Percentage]] -> 35 | P5: =Data[[#This Row],[Marketing Cost Per Unit]]*Data[[#This Row],[Quantity]] -> 12 | Q5: =Data[[#This Row],[Warehouse Cost Per Unit]]*Data[[#This Row],[Quantity]] -> 6 | R5: =Data[[#This Row],[COGS]]+Data[[#This Row],[Marketing Cost]]+Data[[#This Row],[Warehouse Cost]]+Data[[#This Row],[Shipping Cost]] -> 58.5 | S5: =Data[[#This Row],[Revenue]]-Data[[#This Row],[Total Cost]] -> 41.45 | T5: =(Data[[#This Row],[Profit]]/Data[[#This Row],[Revenue]]) -> 0.41470735
A6: 1003 | B6: Ene | C6: Ana López | D6: Pantalón Denim Azul | E6: Bottoms | F6: 1 | G6: 65 | H6: 0 | I6: 7 | J6: Colombia | K6: 0.42 | L6: 5 | M6: 2 | N6: =(Data[[#This Row],[Unit Price]]*Data[[#This Row],[Quantity]])-Data[[#This Row],[Discount]] -> 65 | O6: =Data[[#This Row],[Unit Price]]*Data[[#This Row],[Quantity]]*Data[[#This Row],[Cogs Percentage]] -> 27.3 | P6: =Data[[#This Row],[Marketing Cost Per Unit]]*Data[[#This Row],[Quantity]] -> 5 | Q6: =Data[[#This Row],[Warehouse Cost Per Unit]]*Data[[#This Row],[Quantity]] -> 2 | R6: =Data[[#This Row],[COGS]]+Data[[#This Row],[Marketing Cost]]+Data[[#This Row],[Warehouse Cost]]+Data[[#This Row],[Shipping Cost]] -> 41.3 | S6: =Data[[#This Row],[Revenue]]-Data[[#This Row],[Total Cost]] -> 23.7 | T6: =(Data[[#This Row],[Profit]]/Data[[#This Row],[Revenue]]) -> 0.36461538
A7: 1004 | B7: Ene | C7: Pedro Martínez | D7: Pantalón Denim Azul | E7: Bottoms | F7: 2 | G7: 65 | H7: 0.065 | I7: 7 | J7: Costa Rica | K7: 0.42 | L7: 5 | M7: 2 | N7: =(Data[[#This Row],[Unit Price]]*Data[[#This Row],[Quantity]])-Data[[#This Row],[Discount]] -> 129.935 | O7: =Data[[#This Row],[Unit Price]]*Data[[#This Row],[Quantity]]*Data[[#This Row],[Cogs Percentage]] -> 54.6 | P7: =Data[[#This Row],[Marketing Cost Per Unit]]*Data[[#This Row],[Quantity]] -> 10 | Q7: =Data[[#This Row],[Warehouse Cost Per Unit]]*Data[[#This Row],[Quantity]] -> 4 | R7: =Data[[#This Row],[COGS]]+Data[[#This Row],[Marketing Cost]]+Data[[#This Row],[Warehouse Cost]]+Data[[#This Row],[Shipping Cost]] -> 75.6 | S7: =Data[[#This Row],[Revenue]]-Data[[#This Row],[Total Cost]] -> 54.335 | T7: =(Data[[#This Row],[Profit]]/Data[[#This Row],[Revenue]]) -> 0.41817062
A8: 1009 | B8: Ene | C8: Miguel Santos | D8: Pantalón Denim Azul | E8: Bottoms | F8: 1 | G8: 65 | H8: 0 | I8: 7 | J8: Costa Rica | K8: 0.42 | L8: 5 | M8: 2 | N8: =(Data[[#This Row],[Unit Price]]*Data[[#This Row],[Quantity]])-Data[[#This Row],[Discount]] -> 65 | O8: =Data[[#This Row],[Unit Price]]*Data[[#This Row],[Quantity]]*Data[[#This Row],[Cogs Percentage]] -> 27.3 | P8: =Data[[#This Row],[Marketing Cost Per Unit]]*Data[[#This Row],[Quantity]] -> 5 | Q8: =Data[[#This Row],[Warehouse Cost Per Unit]]*Data[[#This Row],[Quantity]] -> 2 | R8: =Data[[#This Row],[COGS]]+Data[[#This Row],[Marketing Cost]]+Data[[#This Row],[Warehouse Cost]]+Data[[#This Row],[Shipping Cost]] -> 41.3 | S8: =Data[[#This Row],[Revenue]]-Data[[#This Row],[Total Cost]] -> 23.7 | T8: =(Data[[#This Row],[Profit]]/Data[[#This Row],[Revenue]]) -> 0.36461538
A9: 1005 | B9: Ene | C9: Maria Gonzalez | D9: Sudadera Oversized Gris | E9: Outerwear | F9: 1 | G9: 45 | H9: 0 | I9: 6 | J9: Costa Rica | K9: 0.38 | L9: 4.5 | M9: 2.5 | N9: =(Data[[#This Row],[Unit Price]]*Data[[#This Row],[Quantity]])-Data[[#This Row],[Discount]] -> 45 | O9: =Data[[#This Row],[Unit Price]]*Data[[#This Row],[Quantity]]*Data[[#This Row],[Cogs Percentage]] -> 17.1 | P9: =Data[[#This Row],[Marketing Cost Per Unit]]*Data[[#This Row],[Quantity]] -> 4.5 | Q9: =Data[[#This Row],[Warehouse Cost Per Unit]]*Data[[#This Row],[Quantity]] -> 2.5 | R9: =Data[[#This Row],[COGS]]+Data[[#This Row],[Marketing Cost]]+Data[[#This Row],[Warehouse Cost]]+Data[[#This Row],[Shipping Cost]] -> 30.1 | S9: =Data[[#This Row],[Revenue]]-Data[[#This Row],[Total Cost]] -> 14.9 | T9: =(Data[[#This Row],[Profit]]/Data[[#This Row],[Revenue]]) -> 0.33111111
A10: 1012 | B10: Ene | C10: Valentina Cruz | D10: Sudadera Oversized Gris | E10: Outerwear | F10: 2 | G10: 45 | H10: 0.045 | I10: 6 | J10: Colombia | K10: 0.38 | L10: 4.5 | M10: 2.5 | N10: =(Data[[#This Row],[Unit Price]]*Data[[#This Row],[Quantity]])-Data[[#This Row],[Discount]] -> 89.955 | O10: =Data[[#This Row],[Unit Price]]*Data[[#This Row],[Quantity]]*Data[[#This Row],[Cogs Percentage]] -> 34.2 | P10: =Data[[#This Row],[Marketing Cost Per Unit]]*Data[[#This Row],[Quantity]] -> 9 | Q10: =Data[[#This Row],[Warehouse Cost Per Unit]]*Data[[#This Row],[Quantity]] -> 5 | R10: =Data[[#This Row],[COGS]]+Data[[#This Row],[Marketing Cost]]+Data[[#This Row],[Warehouse Cost]]+Data[[#This Row],[Shipping Cost]] -> 54.2 | S10: =Data[[#This Row],[Revenue]]-Data[[#This Row],[Total Cost]] -> 35.755 | T10: =(Data[[#This Row],[Profit]]/Data[[#This Row],[Revenue]]) -> 0.39747652
A11: 1007 | B11: Ene | C11: Carlos Ruiz | D11: Vestido Midi Floral | E11: Dresses | F11: 1 | G11: 55 | H11: 0 | I11: 6.5 | J11: Mexico | K11: 0.4 | L11: 6 | M11: 2 | N11: =(Data[[#This Row],[Unit Price]]*Data[[#This Row],[Quantity]])-Data[[#This Row],[Discount]] -> 55 | O11: =Data[[#This Row],[Unit Price]]*Data[[#This Row],[Quantity]]*Data[[#This Row],[Cogs Percentage]] -> 22 | P11: =Data[[#This Row],[Marketing Cost Per Unit]]*Data[[#This Row],[Quantity]] -> 6 | Q11: =Data[[#This Row],[Warehouse Cost Per Unit]]*Data[[#This Row],[Quantity]] -> 2 | R11: =Data[[#This Row],[COGS]]+Data[[#This Row],[Marketing Cost]]+Data[[#This Row],[Warehouse Cost]]+Data[[#This Row],[Shipping Cost]] -> 36.5 | S11: =Data[[#This Row],[Revenue]]-Data[[#This Row],[Total Cost]] -> 18.5 | T11: =(Data[[#This Row],[Profit]]/Data[[#This Row],[Revenue]]) -> 0.33636364
A12: 1014 | B12: Ene | C12: Isabella Vargas | D12: Vestido Midi Floral | E12: Dresses | F12: 1 | G12: 55 | H12: 0 | I12: 6.5 | J12: Panama | K12: 0.4 | L12: 6 | M12: 2 | N12: =(Data[[#This Row],[Unit Price]]*Data[[#This Row],[Quantity]])-Data[[#This Row],[Discount]] -> 55 | O12: =Data[[#This Row],[Unit Price]]*Data[[#This Row],[Quantity]]*Data[[#This Row],[Cogs Percentage]] -> 22 | P12: =Data[[#This Row],[Marketing Cost Per Unit]]*Data[[#This Row],[Quantity]] -> 6 | Q12: =Data[[#This Row],[Warehouse Cost Per Unit]]*Data[[#This Row],[Quantity]] -> 2 | R12: =Data[[#This Row],[COGS]]+Data[[#This Row],[Marketing Cost]]+Data[[#This Row],[Warehouse Cost]]+Data[[#This Row],[Shipping Cost]] -> 36.5 | S12: =Data[[#This Row],[Revenue]]-Data[[#This Row],[Total Cost]] -> 18.5 | T12: =(Data[[#This Row],[Profit]]/Data[[#This Row],[Revenue]]) -> 0.33636364
A13: 1008 | B13: Feb | C13: Laura Jimenez | D13: Chaqueta Denim Clásica | E13: Outerwear | F13: 1 | G13: 75 | H13: 0.075 | I13: 8 | J13: Colombia | K13: 0.45 | L13: 7 | M13: 3 | N13: =(Data[[#This Row],[Unit Price]]*Data[[#This Row],[Quantity]])-Data[[#This Row],[Discount]] -> 74.925 | O13: =Data[[#This Row],[Unit Price]]*Data[[#This Row],[Quantity]]*Data[[#This Row],[Cogs Percentage]] -> 33.75 | P13: =Data[[#This Row],[Marketing Cost Per Unit]]*Data[[#This Row],[Quantity]] -> 7 | Q13: =Data[[#This Row],[Warehouse Cost Per Unit]]*Data[[#This Row],[Quantity]] -> 3 | R13: =Data[[#This Row],[COGS]]+Data[[#This Row],[Marketing Cost]]+Data[[#This Row],[Warehouse Cost]]+Data[[#This Row],[Shipping Cost]] -> 51.75 | S13: =Data[[#This Row],[Revenue]]-Data[[#This Row],[Total Cost]] -> 23.175 | T13: =(Data[[#This Row],[Profit]]/Data[[#This Row],[Revenue]]) -> 0.30930931
... A41: 1040 | B41: Ene | C41: Raul Aguilar | D41: Camiseta Básica Negra | E41: Tops | F41: 4 | G41: 25 | H41: 0.05 | I41: 5.5 | J41: Colombia | K41: 0.35 | L41: 3 | M41: 1.5 | N41: =(Data[[#This Row],[Unit Price]]*Data[[#This Row],[Quantity]])-Data[[#This Row],[Discount]] -> 99.95 | O41: =Data[[#This Row],[Unit Price]]*Data[[#This Row],[Quantity]]*Data[[#This Row],[Cogs Percentage]] -> 35 | P41: =Data[[#This Row],[Marketing Cost Per Unit]]*Data[[#This Row],[Quantity]] -> 12 | Q41: =Data[[#This Row],[Warehouse Cost Per Unit]]*Data[[#This Row],[Quantity]] -> 6 | R41: =Data[[#This Row],[COGS]]+Data[[#This Row],[Marketing Cost]]+Data[[#This Row],[Warehouse Cost]]+Data[[#This Row],[Shipping Cost]] -> 58.5 | S41: =Data[[#This Row],[Revenue]]-Data[[#This Row],[Total Cost]] -> 41.45 | T41: =(Data[[#This Row],[Profit]]/Data[[#This Row],[Revenue]]) -> 0.41470735

Sheet Notes
A1: KEY INSIGHTS FOR ABROAD PRESENTATION
A3: 1. TOP PRODUCT IN COSTA RICA Pantalón Denim Azul dominated Costa Rican sales in January, representing 56% of revenue ($194.94). This product consistently performs well in this market.
A7: 2. COSTA RICA SALES DECLINE Sales in Costa Rica dropped 67% in February. Investigation needed to determine if this was seasonal, competitive pressure, or operational issue.
A11: 3. MEXICO GROWTH TREND Mexico showed strong sales growth from February to March, driven primarily by dresses and tops. Vestido Midi Floral increased ~50% month-over-month, suggesting successful product-market fit.
A16: 4. COLOMBIA OPPORTUNITY Vestido Midi Floral shows zero in Colombia despite strong permance in Mexico. Recommed testing this product in Colombia market or investigating barriers to entry.

Sheet Sheet3
A3: Month | B3: Sum of Revenue | F3: KPIs
A4: Ene | B4: 914.7275 | F4: Total Revenue | I4: =SUM(Data[Revenue]) -> 2598.945
A5: Feb | B5: 784.615 | F5: Total Profit | I5: =SUM(Data[Profit]) -> 934.395
A6: Mar | B6: 899.6025 | F6: Average Order Value | I6: =SUM(Data[Revenue])/COUNTA(Data[Order id]) -> 64.973625
A7: Grand Total | B7: 2598.945 | F7: Total Orders | I7: =COUNT(Data[Order id]) -> 40
A11: Product Name | B11: Sum of Revenue
A12: Pantalón Denim Azul | B12: 324.87
A13: Camiseta Básica Negra | B13: 274.9
A14: Vestido Midi Floral | B14: 274.89
A15: Camiseta Básica Blanca | B15: 274.875
A16: Sudadera Oversized Gris | B16: 224.91
A17: Grand Total | B17: 1374.445
A27: Country | B27: Sum of Revenue
A28: Colombia | B28: 704.725
A29: Costa Rica | B29: 759.8225
A30: Mexico | B30: 574.69
A31: Panama | B31: 559.7075
A32: Grand Total | B32: 2598.945
A36: Category | B36: Average of Margin%
A37: Bottoms | B37: 0.35137776
A38: Dresses | B38: 0.34871575
A39: Outerwear | B39: 0.32923119
A40: Tops | B40: 0.35926448
A41: Grand Total | B41: 0.34882238
